Workbook

Sheet Needs Assessment
A1: ONYX ACCOUNTING GROUP — CLIENT NEEDS ASSESSMENT
A2: How to use: 1) During the meeting, glance down the list to make sure every area is discussed — no need to type. 2) After the call, paste the transcript into the Transcript tab. 3) The “In transcript?” column auto-flags topics that came up; fill Yes/No + Notes from there.
A3: Assessment category | B3: Yes / No | C3: Notes / Advisories | D3: Help resources | E3: In transcript? | F3: keyword(helper)
A4: Sales and accounts receivable
A5: Estimates | D5: When to use Estimates | E5: =IF($F5="","",IF(COUNTIF(Transcript!$A$4:$A$5000,"*"&$F5&"*")>0,"✓ mentioned","")) | F5: estimate
A6: Simple invoices (no customer tracking) | D6: Simple invoicing in QuickBooks Self-Employed
A7: Custom invoices (accounts receivable tracking) | D7: When to use Invoices
A8: Sales receipts | D8: When to use Sales Receipts | E8: =IF($F8="","",IF(COUNTIF(Transcript!$A$4:$A$5000,"*"&$F8&"*")>0,"✓ mentioned","")) | F8: sales receipt
A9: Statements | D9: When to use Statements
A10: Sales tax (list states in notes/advisory column) | D10: How to set up Sales Tax | E10: =IF($F10="","",IF(COUNTIF(Transcript!$A$4:$A$5000,"*"&$F10&"*")>0,"✓ mentioned","")) | F10: sales tax
A11: Price levels | D11: When to use Price Rules | E11: =IF($F11="","",IF(COUNTIF(Transcript!$A$4:$A$5000,"*"&$F11&"*")>0,"✓ mentioned","")) | F11: price level
A12: Progress invoicing | D12: When to use Progress Invoicing | E12: =IF($F12="","",IF(COUNTIF(Transcript!$A$4:$A$5000,"*"&$F12&"*")>0,"✓ mentioned","")) | F12: progress invoic
A13: Multicurrency | D13: Understanding Multicurrency | E13: =IF($F13="","",IF(COUNTIF(Transcript!$A$4:$A$5000,"*"&$F13&"*")>0,"✓ mentioned","")) | F13: currenc
A14: Average number of transactions per month
A15: Expenses and accounts payable
A16: Accrual-based (bills and bill payments) | D16: When to use bills, checks, and expenses | E16: =IF($F16="","",IF(COUNTIF(Transcript!$A$4:$A$5000,"*"&$F16&"*")>0,"✓ mentioned","")) | F16: accrual
A17: Approvals | D17: Apps to manage Accounts Payable Approvals | E17: =IF($F17="","",IF(COUNTIF(Transcript!$A$4:$A$5000,"*"&$F17&"*")>0,"✓ mentioned","")) | F17: approval
A18: Checks (indicate manual, printed, or both in notes/advisory column) | D18: How to write a check | E18: =IF($F18="","",IF(COUNTIF(Transcript!$A$4:$A$5000,"*"&$F18&"*")>0,"✓ mentioned","")) | F18: check
A19: Credit card expenses | D19: Record an expense | E19: =IF($F19="","",IF(COUNTIF(Transcript!$A$4:$A$5000,"*"&$F19&"*")>0,"✓ mentioned","")) | F19: credit card
A20: Electronic payments | D20: Bill Pay in QuickBooks Online
A21: Loans (list types in notes/advisory column) | D21: How to record a loan and its payment | E21: =IF($F21="","",IF(COUNTIF(Transcript!$A$4:$A$5000,"*"&$F21&"*")>0,"✓ mentioned","")) | F21: loan
A22: Multicurrency | D22: About multicurrency in QuickBooks | E22: =IF($F22="","",IF(COUNTIF(Transcript!$A$4:$A$5000,"*"&$F22&"*")>0,"✓ mentioned","")) | F22: currenc
A23: Separation of personal and business expenses in same bank/credit card account | D23: Separating personal from business finance | E23: =IF($F23="","",IF(COUNTIF(Transcript!$A$4:$A$5000,"*"&$F23&"*")>0,"✓ mentioned","")) | F23: personal
A24: Petty cash expenses | D24: Set up and track Petty Cash | E24: =IF($F24="","",IF(COUNTIF(Transcript!$A$4:$A$5000,"*"&$F24&"*")>0,"✓ mentioned","")) | F24: petty cash
A25: Purchase orders | D25: How to use a Purchase Order | E25: =IF($F25="","",IF(COUNTIF(Transcript!$A$4:$A$5000,"*"&$F25&"*")>0,"✓ mentioned","")) | F25: purchase order
A26: Track vendors for 1099 reporting | D26: How to track 1099 Contractors | E26: =IF($F26="","",IF(COUNTIF(Transcript!$A$4:$A$5000,"*"&$F26&"*")>0,"✓ mentioned","")) | F26: 1099
A27: Billable/Reimbursable expenses | D27: How to enter billable expenses | E27: =IF($F27="","",IF(COUNTIF(Transcript!$A$4:$A$5000,"*"&$F27&"*")>0,"✓ mentioned","")) | F27: reimburs
A28: Electronic receipt/bill capture | D28: How to use Receipt Capture | E28: =IF($F28="","",IF(COUNTIF(Transcript!$A$4:$A$5000,"*"&$F28&"*")>0,"✓ mentioned","")) | F28: receipt
A29: Average number of transactions per month
A30: Employees and payroll
A31: Active workers’ compensation insurance | D31: Learn about workers’ comp insurance | E31: =IF($F31="","",IF(COUNTIF(Transcript!$A$4:$A$5000,"*"&$F31&"*")>0,"✓ mentioned","")) | F31: workers
A32: Number of employees on payroll
A33: Partners/Shareholders on payroll | E33: =IF($F33="","",IF(COUNTIF(Transcript!$A$4:$A$5000,"*"&$F33&"*")>0,"✓ mentioned","")) | F33: shareholder
A34: PTO/Sick/Vacation policy | D34: Add vacation or sick leave policies | E34: =IF($F34="","",IF(COUNTIF(Transcript!$A$4:$A$5000,"*"&$F34&"*")>0,"✓ mentioned","")) | F34: vacation
A35: Retirement plan | D35: Set up retirement deductions and contributions | E35: =IF($F35="","",IF(COUNTIF(Transcript!$A$4:$A$5000,"*"&$F35&"*")>0,"✓ mentioned","")) | F35: retirement
A36: Time tracking (indicate vendors, employees, or both in notes/advisory column) | D36: How to turn on and set up time tracking | E36: =IF($F36="","",IF(COUNTIF(Transcript!$A$4:$A$5000,"*"&$F36&"*")>0,"✓ mentioned","")) | F36: time tracking
A37: Average number of transactions per month
A38: Other expense-tracking needs
A39: Estimated income taxes | D39: Quarterly Estimated Taxes Explained | E39: =IF($F39="","",IF(COUNTIF(Transcript!$A$4:$A$5000,"*"&$F39&"*")>0,"✓ mentioned","")) | F39: estimated tax
A40: Mileage tracking—if yes, then complete the vehicle profile on the Mileage tab | D40: What Is Mileage Tracking? | E40: =IF($F40="","",IF(COUNTIF(Transcript!$A$4:$A$5000,"*"&$F40&"*")>0,"✓ mentioned","")) | F40: mileage
A41: Other daily operations needs
A42: Inventory tracking—FIFO method | D42: What is FIFO and how is it used | E42: =IF($F42="","",IF(COUNTIF(Transcript!$A$4:$A$5000,"*"&$F42&"*")>0,"✓ mentioned","")) | F42: fifo
A43: Inventory tracking—other methods (indicate method in notes/advisories) | D43: Inventory Valuation Method Comparison | E43: =IF($F43="","",IF(COUNTIF(Transcript!$A$4:$A$5000,"*"&$F43&"*")>0,"✓ mentioned","")) | F43: inventory
A44: Industry-specific needs
A45: Asset management | D45: Managing assets in QuickBooks | E45: =IF($F45="","",IF(COUNTIF(Transcript!$A$4:$A$5000,"*"&$F45&"*")>0,"✓ mentioned","")) | F45: asset
A46: Billable time | D46: How to turn on and set up time tracking | E46: =IF($F46="","",IF(COUNTIF(Transcript!$A$4:$A$5000,"*"&$F46&"*")>0,"✓ mentioned","")) | F46: billable
A47: Customer Relationship Management (CRM) for sales team | D47: CRM apps on apps.com | E47: =IF($F47="","",IF(COUNTIF(Transcript!$A$4:$A$5000,"*"&$F47&"*")>0,"✓ mentioned","")) | F47: crm
A48: E-commerce/Web-based sales | D48: All you need to know about eCommerce Bookkeeping | E48: =IF($F48="","",IF(COUNTIF(Transcript!$A$4:$A$5000,"*"&$F48&"*")>0,"✓ mentioned","")) | F48: commerce
A49: EDI (electronic data interchange) | D49: Apps to manage EDI | E49: =IF($F49="","",IF(COUNTIF(Transcript!$A$4:$A$5000,"*"&$F49&"*")>0,"✓ mentioned","")) | F49: electronic data
A50: Field service | D50: Apps to manage field service | E50: =IF($F50="","",IF(COUNTIF(Transcript!$A$4:$A$5000,"*"&$F50&"*")>0,"✓ mentioned","")) | F50: field service
A51: Kitting/Bundled items | D51: Bundles in QuickBooks | E51: =IF($F51="","",IF(COUNTIF(Transcript!$A$4:$A$5000,"*"&$F51&"*")>0,"✓ mentioned","")) | F51: bundle
A52: Logistics/Distribution/3PL | D52: Apps to manage 3PL logistics | E52: =IF($F52="","",IF(COUNTIF(Transcript!$A$4:$A$5000,"*"&$F52&"*")>0,"✓ mentioned","")) | F52: logistics
A53: Manufacturing/inventory assembly | D53: Apps to manage manufacturing | E53: =IF($F53="","",IF(COUNTIF(Transcript!$A$4:$A$5000,"*"&$F53&"*")>0,"✓ mentioned","")) | F53: manufactur
A54: Point of sale/cash register | D54: Apps to manage Point of Sale | E54: =IF($F54="","",IF(COUNTIF(Transcript!$A$4:$A$5000,"*"&$F54&"*")>0,"✓ mentioned","")) | F54: point of sale
A55: Shipping and receiving | D55: Apps to manage shipping | E55: =IF($F55="","",IF(COUNTIF(Transcript!$A$4:$A$5000,"*"&$F55&"*")>0,"✓ mentioned","")) | F55: shipping
A56: Specialized application needs (apps)
A57: Accounts receivable collections | D57: Apps to manage Accounts Receivable | E57: =IF($F57="","",IF(COUNTIF(Transcript!$A$4:$A$5000,"*"&$F57&"*")>0,"✓ mentioned","")) | F57: collection
A58: Billing: wholesale vs independent | D58: Apps to manage Wholesale Distribution | E58: =IF($F58="","",IF(COUNTIF(Transcript!$A$4:$A$5000,"*"&$F58&"*")>0,"✓ mentioned","")) | F58: wholesale
A59: Document cloud storage | D59: Apps to manage Document Storage | E59: =IF($F59="","",IF(COUNTIF(Transcript!$A$4:$A$5000,"*"&$F59&"*")>0,"✓ mentioned","")) | F59: cloud storage
A60: Document collection & management | D60: Apps to manage Document Collection
A61: Electronic bill pay | D61: Apps to manage Bill Pay | E61: =IF($F61="","",IF(COUNTIF(Transcript!$A$4:$A$5000,"*"&$F61&"*")>0,"✓ mentioned","")) | F61: bill pay
A62: Merchant services/payment processing | D62: Apps to manage Payment Processing | E62: =IF($F62="","",IF(COUNTIF(Transcript!$A$4:$A$5000,"*"&$F62&"*")>0,"✓ mentioned","")) | F62: merchant
A63: Time tracking approval & GPS | D63: Apps to manage robust Time Tracking | E63: =IF($F63="","",IF(COUNTIF(Transcript!$A$4:$A$5000,"*"&$F63&"*")>0,"✓ mentioned","")) | F63: gps
A64: Reporting needs
A65: Budgeting | D65: How to create, edit, and manage budgets | E65: =IF($F65="","",IF(COUNTIF(Transcript!$A$4:$A$5000,"*"&$F65&"*")>0,"✓ mentioned","")) | F65: budget
A66: Cash flow forecasting | D66: Apps for Cash Flow Forecasting | E66: =IF($F66="","",IF(COUNTIF(Transcript!$A$4:$A$5000,"*"&$F66&"*")>0,"✓ mentioned","")) | F66: forecast
A67: Consolidated reporting | D67: Apps for Consolidated Reporting | E67: =IF($F67="","",IF(COUNTIF(Transcript!$A$4:$A$5000,"*"&$F67&"*")>0,"✓ mentioned","")) | F67: consolidat
A68: Customer/Job profitability | D68: Set up and use Projects | E68: =IF($F68="","",IF(COUNTIF(Transcript!$A$4:$A$5000,"*"&$F68&"*")>0,"✓ mentioned","")) | F68: profitab
A69: Monthly financial statements required | D69: Management Reports | E69: =IF($F69="","",IF(COUNTIF(Transcript!$A$4:$A$5000,"*"&$F69&"*")>0,"✓ mentioned","")) | F69: financial statement
A70: Multiple sources of revenue (product lines, revenue streams, departments, partners, etc.) | D70: When to use Classes and Locations | E70: =IF($F70="","",IF(COUNTIF(Transcript!$A$4:$A$5000,"*"&$F70&"*")>0,"✓ mentioned","")) | F70: product line
A71: Project/Job tracking | D71: Set up and use Projects | E71: =IF($F71="","",IF(COUNTIF(Transcript!$A$4:$A$5000,"*"&$F71&"*")>0,"✓ mentioned","")) | F71: project
A72: Reports only access users | D72: Types of users
A73: Track multiple locations (enter # of locations in notes/advisories column) | D73: When to use Classes and Locations | E73: =IF($F73="","",IF(COUNTIF(Transcript!$A$4:$A$5000,"*"&$F73&"*")>0,"✓ mentioned","")) | F73: location
A74: Trial balance | D74: What is a Trial Balance? | E74: =IF($F74="","",IF(COUNTIF(Transcript!$A$4:$A$5000,"*"&$F74&"*")>0,"✓ mentioned","")) | F74: trial balance
A75: Other
A76: Conversion from previous accounting solution | D76: Convert from QuickBooks Desktop to Online
A77: Number of users needed | D77: Multiple Users in QuickBooks
A78: Total number of transactions per month:
A79: Sales and accounts receivable
A80: Expenses and accounts payable
A81: Payroll

Sheet Transcript
A1: MEETING TRANSCRIPT
A2: Paste the full meeting transcript below, starting in cell A4 (Ctrl+V). It is fine if it splits across many rows — the Needs Assessment tab scans all of it.
